pyrediseasyio/__init__.py
pyrediseasyio/abstract_reader_writer.py
pyrediseasyio/reader_writer.py
pyrediseasyio/html/__init__.py
pyrediseasyio/html/html_io.py
pyrediseasyio/html/html_io_group.py
pyrediseasyio/io/__init__.py
pyrediseasyio/io/boolean_io.py
pyrediseasyio/io/float_io.py
pyrediseasyio/io/integer_io.py
pyrediseasyio/io/io_group.py
pyrediseasyio/io/numeric_io.py
pyrediseasyio/io/single_io.py
pyrediseasyio/io/string_io.py
pyrediseasyio/io/trigger_io.py
tests/__init__.py
tests/test_get_attributes.py
tests/test_html_io.py
tests/test_html_io_group.py
tests/test_html_io_group_conversion.py
tests/test_operator_overloads.py
tests/test_pub_sub.py
tests/test_read_write.py
tests/test_trigger_io.py
tests/hmi/__init__.py
tests/hmi/app.py
tests/hmi/keyboard.py
pyrediseasyio-0.0.35.dist-info/LICENSE
pyrediseasyio-0.0.35.dist-info/METADATA
pyrediseasyio-0.0.35.dist-info/WHEEL
pyrediseasyio-0.0.35.dist-info/top_level.txt
pyrediseasyio-0.0.35.dist-info/RECORD
