Metadata-Version: 2.1
Name: pyrediseasyio
Version: 0.0.35
Summary: A set of tools for simplifying reading and writing of single values to/from Redis.
Home-page: https://github.com/washad/PyRedisEasyIO
Author: Steve Jackson
Author-email: washad@gmail.com
License: UNKNOWN
Platform: UNKNOWN
Classifier: Programming Language :: Python :: 3
Classifier: License :: OSI Approved :: MIT License
Classifier: Operating System :: OS Independent
Requires-Dist: wheel
Requires-Dist: dominate
Requires-Dist: redis
Requires-Dist: str2bool
